unitypackff/__init__.py
unitypackff/asset.py
unitypackff/assetbundle.py
unitypackff/classes.json
unitypackff/enums.py
unitypackff/environment.py
unitypackff/export.py
unitypackff/modding.py
unitypackff/object.py
unitypackff/resources.py
unitypackff/strings.dat
unitypackff/structs.dat
unitypackff/type.py
unitypackff/utils.py
unitypackff/engine/__init__.py
unitypackff/engine/animation.py
unitypackff/engine/audio.py
unitypackff/engine/component.py
unitypackff/engine/font.py
unitypackff/engine/mesh.py
unitypackff/engine/movie.py
unitypackff/engine/object.py
unitypackff/engine/particle.py
unitypackff/engine/physics.py
unitypackff/engine/renderer.py
unitypackff/engine/text.py
unitypackff/engine/texture.py
unitypackff-1.0.4.data/scripts/additem.py
unitypackff-1.0.4.data/scripts/addmission.py
unitypackff-1.0.4.data/scripts/dump_terrain.py
unitypackff-1.0.4.data/scripts/dumpxdt.py
unitypackff-1.0.4.data/scripts/ffextract.py
unitypackff-1.0.4.data/scripts/list_ab_alt.py
unitypackff-1.0.4.data/scripts/list_assetbundle.py
unitypackff-1.0.4.data/scripts/list_contents.py
unitypackff-1.0.4.data/scripts/replace_mesh.py
unitypackff-1.0.4.data/scripts/replace_terrain.py
unitypackff-1.0.4.data/scripts/show_gameobject.py
unitypackff-1.0.4.data/scripts/unity2yaml.py
unitypackff-1.0.4.data/scripts/unityextract.py
unitypackff-1.0.4.dist-info/LICENSE
unitypackff-1.0.4.dist-info/METADATA
unitypackff-1.0.4.dist-info/WHEEL
unitypackff-1.0.4.dist-info/top_level.txt
unitypackff-1.0.4.dist-info/RECORD
