Metadata-Version: 2.1
Name: unitypackff
Version: 1.0.4
Summary: UnityPackFF is a fork of UnityPack specialized for working with FusionFall assets
Home-page: https://github.com/SirDank/UnityPackFF
Download-URL: https://github.com/SirDank/UnityPackFF/tarball/master
Author: dongresource
License: MIT
Project-URL: GitHub, https://github.com/SirDank/UnityPackFF
Project-URL: Bug Tracker, https://github.com/SirDank/UnityPackFF/issues
Keywords: unity,unitypack,unitypackff
Classifier: Development Status :: 4 - Beta
Classifier: Intended Audience :: Developers
Classifier: License :: OSI Approved :: MIT License
Classifier: Programming Language :: Python
Classifier: Programming Language :: Python :: 3
Classifier: Programming Language :: Python :: 3.4
Classifier: Programming Language :: Python :: 3.5
Classifier: Programming Language :: Python :: 3.6
Classifier: Topic :: Multimedia :: Graphics
License-File: LICENSE
Requires-Dist: fsb5
Requires-Dist: lz4
Requires-Dist: Pillow
Requires-Dist: wand
